{"book_id": "77", "title": "The House of the Seven Gables by Nathaniel Hawthorne", "author": "110 by Nathaniel Hawthorne", "names_only": true, "characters": [{"name": "Matthew Maule", "mentions": 7}, {"name": "Nathaniel Hawthorne", "mentions": 5}, {"name": "Hawthorne", "mentions": 3}, {"name": "Colonel Pyncheon", "mentions": 3}, {"name": "John Hathorne", "mentions": 2}, {"name": "Philip English", "mentions": 2}, {"name": "Phœbe", "mentions": 2}, {"name": "Clifford Pyncheon", "mentions": 2}, {"name": "Alice Pyncheon", "mentions": 2}, {"name": "Maule", "mentions": 2}, {"name": "George Parsons Lathrop", "mentions": 1}, {"name": "Judith Boss", "mentions": 1}, {"name": "Al Haines", "mentions": 1}, {"name": "Holgrave", "mentions": 1}, {"name": "Mrs. Hawthorne", "mentions": 1}, {"name": "G. P. L.", "mentions": 1}, {"name": "LENOX", "mentions": 1}], "interactions": [{"from": "Hawthorne", "to": "Mrs. Hawthorne", "count": 2, "strength": 2}, {"from": "Colonel Pyncheon", "to": "Matthew Maule", "count": 2, "strength": -2}]}